{
  ".txt": "Plain text file",
  ".md": "Markdown text",
  ".rst": "reStructuredText",
  ".pdf": "PDF document",
  ".doc": "Word document (old)",
  ".docx": "Word document",
  ".odt": "OpenDocument text",
  ".rtf": "Rich text file",
  ".tex": "LaTeX source",
  ".log": "Log file",
  ".epub": "E-book file",
  ".py": "Python script",
  ".ipynb": "Jupyter notebook",
  ".java": "Java source",
  ".c": "C source",
  ".h": "C/C++ header",
  ".cpp": "C++ source",
  ".hpp": "C++ header",
  ".cs": "C# source",
  ".php": "PHP script",
  ".rb": "Ruby script",
  ".go": "Go source",
  ".rs": "Rust source",
  ".swift": "Swift source",
  ".kt": "Kotlin source",
  ".kts": "Kotlin script",
  ".scala": "Scala source",
  ".sh": "Shell script",
  ".bat": "Batch script",
  ".ps1": "PowerShell script",
  ".pl": "Perl script",
  ".lua": "Lua script",
  ".r": "R script",
  ".dart": "Dart source",
  ".ts": "TypeScript source",
  ".tsx": "TypeScript + JSX",
  ".js": "JavaScript file",
  ".jsx": "JavaScript + JSX",
  ".coffee": "CoffeeScript file",
  ".groovy": "Groovy script",
  ".vb": "Visual Basic file",
  ".m": "Objective-C or MATLAB",
  ".asm": "Assembly source",
  ".for": "Fortran source",
  ".f90": "Fortran 90 source",
  ".erl": "Erlang source",
  ".ex": "Elixir source",
  ".exs": "Elixir script",
  ".clj": "Clojure source",
  ".cljs": "ClojureScript file",
  ".lisp": "Lisp source",
  ".scm": "Scheme source",
  ".sql": "SQL script",
  ".psql": "PostgreSQL script",
  ".html": "HTML file",
  ".htm": "HTML file",
  ".css": "CSS file",
  ".json": "JSON file",
  ".xml": "XML file",
  ".yml": "YAML file",
  ".yaml": "YAML file",
  ".csv": "CSV file",
  ".tsv": "TSV file",
  ".db": "Database file",
  ".sqlite": "SQLite database",
  ".sqlite3": "SQLite3 database",
  ".exe": "Executable file",
  ".dll": "Dynamic library",
  ".so": "Shared library",
  ".dylib": "macOS library",
  ".bin": "Binary file",
  ".class": "Java bytecode",
  ".jar": "Java archive",
  ".app": "macOS app",
  ".zip": "ZIP archive",
  ".rar": "RAR archive",
  ".7z": "7-Zip archive",
  ".tar": "TAR archive",
  ".gz": "Gzip archive",
  ".bz2": "Bzip2 archive",
  ".xz": "XZ archive",
  ".iso": "Disk image",
  ".dmg": "macOS disk image",
  ".jpg": "JPEG image",
  ".jpeg": "JPEG image",
  ".png": "PNG image",
  ".gif": "GIF image",
  ".bmp": "Bitmap image",
  ".tiff": "TIFF image",
  ".ico": "Icon file",
  ".svg": "SVG image",
  ".webp": "WebP image",
  ".psd": "Photoshop file",
  ".ai": "Illustrator file",
  ".eps": "PostScript file",
  ".mp3": "MP3 audio",
  ".wav": "WAV audio",
  ".flac": "FLAC audio",
  ".aac": "AAC audio",
  ".ogg": "OGG audio",
  ".m4a": "MPEG-4 audio",
  ".wma": "WMA audio",
  ".alac": "Apple Lossless audio",
  ".mp4": "MP4 video",
  ".mov": "QuickTime video",
  ".avi": "AVI video",
  ".mkv": "Matroska video",
  ".flv": "Flash video",
  ".wmv": "WMV video",
  ".webm": "WebM video",
  ".mpeg": "MPEG video",
  ".mpg": "MPEG video",
  ".3gp": "3GPP video",
  ".vob": "DVD video",
  ".ini": "Config file",
  ".cfg": "Config file",
  ".conf": "Config file",
  ".env": "Environment variables",
  ".bak": "Backup file",
  ".tmp": "Temporary file",
  ".ttf": "TrueType font",
  ".otf": "OpenType font",
  ".woff": "Web font",
  ".woff2": "Web font 2",
  ".eot": "Embedded OpenType font",
  ".apk": "Android app",
  ".torrent": "Torrent file",
  ".cmd": "Command script",
  ".ics": "Calendar file",
  ".vcf": "Contact file",
  ".msg": "Outlook message",
  ".eml": "Email file"
}
